setup.py
pyncomb/__init__.py
pyncomb/combfuncs.py
pyncomb/ksubsetcolex.py
pyncomb/ksubsetcolextest.py
pyncomb/ksubsetlex.py
pyncomb/ksubsetlextest.py
pyncomb/ksubsetrevdoor.py
pyncomb/ksubsetrevdoortest.py
pyncomb/mbtuplelex.py
pyncomb/mbtuplelextest.py
pyncomb/permlex.py
pyncomb/permlextest.py
pyncomb/permtj.py
pyncomb/permtjtest.py
pyncomb/subsetgc.py
pyncomb/subsetgctest.py
pyncomb/subsetlex.py
pyncomb/subsetlextest.py
pyncomb/tuplelex.py
pyncomb/tuplelextest.py
pyncomb.egg-info/PKG-INFO
pyncomb.egg-info/SOURCES.txt
pyncomb.egg-info/dependency_links.txt
pyncomb.egg-info/top_level.txt