Metadata-Version: 1.0
Name: pyncomb
Version: 1.0.1
Summary: PYthoN COMBinatorics library
Home-page: http://www.site.uottawa.ca/~mraap046
Author: Sebastian Raaphorst
Author-email: srcoding@gmail.com
License: Apache 2.0
Keywords: mathematics combinatorics permutations combinations subsets
Platform: UNKNOWN
Classifier: License :: OSI Approved :: Apache Software License
Classifier: Programming Language :: Python
Classifier: Development Status :: 4 - Beta
Classifier: Intended Audience :: Developers
Classifier: Topic :: Scientific/Engineering :: Mathematics
